README.txt
TODO.txt
setup.py
src/plone/__init__.py
src/plone.recipe.dzhandle.egg-info/PKG-INFO
src/plone.recipe.dzhandle.egg-info/SOURCES.txt
src/plone.recipe.dzhandle.egg-info/dependency_links.txt
src/plone.recipe.dzhandle.egg-info/entry_points.txt
src/plone.recipe.dzhandle.egg-info/namespace_packages.txt
src/plone.recipe.dzhandle.egg-info/not-zip-safe
src/plone.recipe.dzhandle.egg-info/requires.txt
src/plone.recipe.dzhandle.egg-info/top_level.txt
src/plone/recipe/__init__.py
src/plone/recipe/dzhandle/__init__.py
src/plone/recipe/dzhandle/recipe.py
