Metadata-Version: 1.0
Name: plone.recipe.dzhandle
Version: 1.0-beta2
Summary: ZC Buildout control for Debians zope instance handler 'dzhandle'
Home-page: http://svn.plone.org/svn/collective/buildout/plone.recipe.dzhandle
Author: Jens W. Klein
Author-email: dev@bluedynamics.com
License: ZPL 2.1
Keywords: zope buildout debian dzhandle
Platform: UNKNOWN
Classifier: License :: OSI Approved :: Zope Public License
Classifier: Framework :: Buildout
Classifier: Framework :: Zope2
Classifier: Operating System :: POSIX :: Linux
Classifier: Programming Language :: Python
